[
  {
    "email": "skaiste.urbonaviciene@paysera.net"
  },
  {
    "email": "sofja.lipova@paysera.net"
  },
  {
    "email": "sonata.zinkeviciene@paysera.net"
  },
  {
    "email": "soniya.kumar@paysera.net"
  },
  {
    "email": "sopo.pipia@paysera.net"
  },
  {
    "email": "stanislau.pivavarchyk@paysera.net"
  },
  {
    "email": "stanislav.georgiev@paysera.net"
  },
  {
    "email": "stanislav.kostov@paysera.net"
  },
  {
    "email": "stanislav.nikolov@paysera.net"
  },
  {
    "email": "stanislav.shulha@paysera.net"
  },
  {
    "email": "stanislav.trubchanov@paysera.net"
  },
  {
    "email": "stanislav.zlatkov@paysera.net"
  },
  {
    "email": "stecy.koraomana@paysera.net"
  },
  {
    "email": "stefka.ilieva@paysera.net"
  },
  {
    "email": "stenny.randriamanantsoa@paysera.net"
  },
  {
    "email": "sunny.prasad@paysera.net"
  },
  {
    "email": "svetlana.moiseishina@paysera.net"
  },
  {
    "email": "svetlana.prankaite@paysera.net"
  },
  {
    "email": "svetoslav.nikolov@paysera.net"
  },
  {
    "email": "svitlana.beleshko@paysera.net"
  },
  {
    "email": "sylvio.rasendrahasina@paysera.net"
  },
  {
    "email": "tadas.putjato@paysera.net"
  },
  {
    "email": "tamar.jalagonia@paysera.net"
  },
  {
    "email": "tamara.vovk@paysera.net"
  },
  {
    "email": "tamari.mumladze@paysera.net"
  },
  {
    "email": "tamila.melqadze@paysera.net"
  },
  {
    "email": "tamriko.chechelashvili@paysera.net"
  },
  {
    "email": "tanel.trei@paysera.net"
  },
  {
    "email": "taras.samoilenko@paysera.net"
  },
  {
    "email": "tatia.gilashvili@paysera.net"
  },
  {
    "email": "tatjana.aleksejeva@paysera.net"
  },
  {
    "email": "tatsiana.tsiareshchanka@paysera.net"
  },
  {
    "email": "tatyana.stoyanova@paysera.net"
  },
  {
    "email": "tautvydas.mackevicius@paysera.net"
  },
  {
    "email": "tejas.choksi@paysera.net"
  },
  {
    "email": "temur.malishava@paysera.net"
  },
  {
    "email": "teodor.chakarov@paysera.net"
  },
  {
    "email": "teona.giorgobiani@paysera.net"
  },
  {
    "email": "denis.lisovskis92@gmail.com"
  },
  {
    "email": "thivyaprabha.karthikeyan@paysera.net"
  },
  {
    "email": "tina.lomouri@paysera.net"
  },
  {
    "email": "tinatin.alxanishvili@paysera.net"
  },
  {
    "email": "toky.andriambololona@paysera.net"
  },
  {
    "email": "toma.bingeliene@paysera.net"
  },
  {
    "email": "tomas.ignatjevas@paysera.net"
  },
  {
    "email": "tomas.liubinas@paysera.net"
  },
  {
    "email": "tomas.martinkus@paysera.net"
  },
  {
    "email": "tomas.matulevicius@paysera.net"
  },
  {
    "email": "tomas.slavenskas@paysera.net"
  },
  {
    "email": "tomas.vendzelis@paysera.net"
  }
]